{"t": "Article IX Judicial Branch of Government", "p": "/us/nsn/umitribe/council/constitution/ix", "et": "container", "dj": "/us/nsn/umitribe/council/constitution/index.json", "fh": "/us/nsn/umitribe/council/constitution/ix/index.full.html", "sc": "Article IX", "sp": "library|Constitution of the Upper Mattaponi Tribe|IX", "c": [{"t": "1 Composition", "p": "/us/nsn/umitribe/council/constitution/ix/1", "et": "section", "sc": "Section 1", "sp": "library|Constitution of the Upper Mattaponi Tribe|IX|1"}, {"t": "2 Qualifications", "p": "/us/nsn/umitribe/council/constitution/ix/2", "et": "section", "sc": "Section 2", "sp": "library|Constitution of the Upper Mattaponi Tribe|IX|2"}, {"t": "3 Selection", "p": "/us/nsn/umitribe/council/constitution/ix/3", "et": "section", "sc": "Section 3", "sp": "library|Constitution of the Upper Mattaponi Tribe|IX|3"}, {"t": "4 Terms", "p": "/us/nsn/umitribe/council/constitution/ix/4", "et": "section", "sc": "Section 4", "sp": "library|Constitution of the Upper Mattaponi Tribe|IX|4"}, {"t": "5 Jurisdiction", "p": "/us/nsn/umitribe/council/constitution/ix/5", "et": "section", "sc": "Section 5", "sp": "library|Constitution of the Upper Mattaponi Tribe|IX|5"}, {"t": "6 Powers and Duties", "p": "/us/nsn/umitribe/council/constitution/ix/6", "et": "section", "sc": "Section 6", "sp": "library|Constitution of the Upper Mattaponi Tribe|IX|6", "c": [{"t": "(a)", "p": "/us/nsn/umitribe/council/constitution/ix/6#(a)", "et": "para", "sc": "Section 6(a)", "x": "The Trial Court shall have the power to interpret the Constitution and laws"}, {"t": "(b)", "p": "/us/nsn/umitribe/council/constitution/ix/6#(b)", "et": "para", "sc": "Section 6(b)", "x": "The High Court shall have the power to interpret the Constitution and laws "}, {"t": "(c)", "p": "/us/nsn/umitribe/council/constitution/ix/6#(c)", "et": "para", "sc": "Section 6(c)", "x": "The Trial Court and the High Court shall be courts of record."}]}, {"t": "7 Compensation", "p": "/us/nsn/umitribe/council/constitution/ix/7", "et": "section", "sc": "Section 7", "sp": "library|Constitution of the Upper Mattaponi Tribe|IX|7"}]}